Metadata-Version: 2.4
Name: spicecode
Version: 2.2.0
Summary: SpiceCode: The next generation of code analysis.
Home-page: https://github.com/spicecodecli/spicecode
Author: SpiceCodeCLI
Author-email: spicecodecli@gmail.com
License: Apache-2.0
Classifier: Programming Language :: Python :: 3
Classifier: License :: OSI Approved :: Apache Software License
Classifier: Operating System :: OS Independent
Requires-Python: >=3.7
License-File: LICENSE
Requires-Dist: InquirerPy==0.3.4
Requires-Dist: numpy==2.2.6
Requires-Dist: pytest==8.3.5
Requires-Dist: rich==14.0.0
Requires-Dist: setuptools==78.1.1
Requires-Dist: typer==0.15.4
Dynamic: author
Dynamic: author-email
Dynamic: classifier
Dynamic: description
Dynamic: description-content-type
Dynamic: home-page
Dynamic: license
Dynamic: license-file
Dynamic: requires-dist
Dynamic: requires-python
Dynamic: summary
